[
    {
        "SceneData": {
            "skyBoxGUID": [],
            "NavMeshGuid": "00000000-0000-0000-0000-000000000000",
            "postProcessingProfile": "00000000-0000-0000-0000-000000000000",
            "ambientIntensity": 1.0
        }
    },
    {
        "entityGUID": "36e0f6cf-7d76-0e22-cd3c-3cc344cdf4a6",
        "CameraComponent": {
            "cameraType": 0,
            "fov": 45.0,
            "nearPlane": 0.05000000074505806,
            "farPlane": 200.0,
            "size": {
                "x": 1600.0,
                "y": 900.0
            },
            "target": {
                "x": 0.0,
                "y": 0.0,
                "z": -1.0
            },
            "active": false,
            "culling": false,
            "layer": 0,
            "renderOrder": 0
        },
        "NameComponent": {
            "entityName": "Camera",
            "Layer": 0,
            "entityTag": "Default",
            "isPrefab": false,
            "isStatic": false,
            "prefabName": "",
            "hide": false
        },
        "TransformComponent": {
            "WorldTransformation": {
                "position": {
                    "x": 0.0,
                    "y": 0.0,
                    "z": 0.0
                },
                "rotation": {
                    "x": 0.0,
                    "y": -0.0,
                    "z": 0.0
                },
                "scale": {
                    "x": 2.200000047683716,
                    "y": 1.4500000476837158,
                    "z": 1.0
                }
            },
            "LocalTransformation": {
                "position": {
                    "x": 0.0,
                    "y": 0.0,
                    "z": 0.0
                },
                "rotation": {
                    "x": 0.0,
                    "y": -0.0,
                    "z": 0.0
                },
                "scale": {
                    "x": 2.200000047683716,
                    "y": 1.4500000476837158,
                    "z": 1.0
                }
            }
        }
    },
    {
        "entityGUID": "d16302c7-baec-0283-643a-d50fe3c69fc8",
        "CanvasRendererComponent": {
            "isScreenSpace": true
        },
        "NameComponent": {
            "entityName": "Canvas",
            "Layer": 0,
            "entityTag": "Default",
            "isPrefab": false,
            "isStatic": false,
            "prefabName": "",
            "hide": false
        },
        "TransformComponent": {
            "WorldTransformation": {
                "position": {
                    "x": 0.0,
                    "y": 0.0,
                    "z": 0.705436646938324
                },
                "rotation": {
                    "x": 0.0,
                    "y": -0.0,
                    "z": 0.0
                },
                "scale": {
                    "x": 1.0,
                    "y": 1.0,
                    "z": 1.0
                }
            },
            "LocalTransformation": {
                "position": {
                    "x": 0.0,
                    "y": 0.0,
                    "z": 0.705436646938324
                },
                "rotation": {
                    "x": 0.0,
                    "y": -0.0,
                    "z": 0.0
                },
                "scale": {
                    "x": 1.0,
                    "y": 1.0,
                    "z": 1.0
                }
            }
        },
        "children": [
            {
                "entityGUID": "5b528fb2-c429-b5c0-428d-096501efe657",
                "AudioComponent": {
                    "audioFiles": [
                        {
                            "audioGUID": "843a876a-467e-4f69-e5a2-aa5455a695ec",
                            "volume": 1.0,
                            "loop": false,
                            "playOnStart": false,
                            "hasPlayed": false,
                            "pan": 0.0,
                            "isBGM": false,
                            "isSFX": true,
                            "use3D": false,
                            "minDistance": 1.0,
                            "maxDistance": 20.0,
                            "sourceType": 0,
                            "audioBankGUID": "00000000-0000-0000-0000-000000000000",
                            "studioEventPath": ""
                        }
                    ]
                },
                "CutsceneAutoScript": {
                    "video_GUID": "155a9ebf-7e02-c70e-8851-62da19e75e25",
                    "audio": "843a876a-467e-4f69-e5a2-aa5455a695ec",
                    "next_Scene": "2e36ac0c-c891-a01a-52dd-02ec380c62de"
                },
                "NameComponent": {
                    "entityName": "Script",
                    "Layer": 0,
                    "entityTag": "Default",
                    "isPrefab": false,
                    "isStatic": false,
                    "prefabName": "",
                    "hide": false
                },
                "TransformComponent": {
                    "WorldTransformation": {
                        "position": {
                            "x": 0.0,
                            "y": 0.0,
                            "z": 0.0
                        },
                        "rotation": {
                            "x": 0.0,
                            "y": -0.0,
                            "z": 0.0
                        },
                        "scale": {
                            "x": 1.0,
                            "y": 1.0,
                            "z": 1.0
                        }
                    },
                    "LocalTransformation": {
                        "position": {
                            "x": 0.0,
                            "y": 0.0,
                            "z": -0.705436646938324
                        },
                        "rotation": {
                            "x": 0.0,
                            "y": -0.0,
                            "z": 0.0
                        },
                        "scale": {
                            "x": 1.0,
                            "y": 1.0,
                            "z": 1.0
                        }
                    }
                }
            }
        ]
    },
    {
        "entityGUID": "155a9ebf-7e02-c70e-8851-62da19e75e25",
        "NameComponent": {
            "entityName": "Video",
            "Layer": 0,
            "entityTag": "Default",
            "isPrefab": false,
            "isStatic": false,
            "prefabName": "",
            "hide": false
        },
        "TransformComponent": {
            "WorldTransformation": {
                "position": {
                    "x": 2.4000000953674316,
                    "y": 0.0,
                    "z": 0.0
                },
                "rotation": {
                    "x": 0.0,
                    "y": -89.98021697998047,
                    "z": 0.0
                },
                "scale": {
                    "x": 1.7777777910232544,
                    "y": 1.0,
                    "z": 0.9999995827674866
                }
            },
            "LocalTransformation": {
                "position": {
                    "x": 2.4000000953674316,
                    "y": 0.0,
                    "z": 0.0
                },
                "rotation": {
                    "x": 0.0,
                    "y": -89.9999771118164,
                    "z": 0.0
                },
                "scale": {
                    "x": 1.7777777910232544,
                    "y": 1.0,
                    "z": 0.9999995827674866
                }
            }
        },
        "VideoComponent": {
            "videoGUID": "b2f7926a-e32e-f9de-6ade-8070ab641ba2",
            "pause": false,
            "loop": false
        }
    }
]